EnsemblesOpt/Bayesian.py
EnsemblesOpt/Optuna_Ensembles.py
EnsemblesOpt/__init__.py
EnsemblesOpt-0.1.2.dist-info/License.txt
EnsemblesOpt-0.1.2.dist-info/METADATA
EnsemblesOpt-0.1.2.dist-info/WHEEL
EnsemblesOpt-0.1.2.dist-info/top_level.txt
EnsemblesOpt-0.1.2.dist-info/RECORD
